setup.py
lust/__init__.py
lust/config.py
lust/log.py
lust/server.py
lust/tail.py
lust/unix.py
python_lust.egg-info/PKG-INFO
python_lust.egg-info/SOURCES.txt
python_lust.egg-info/dependency_links.txt
python_lust.egg-info/top_level.txt