Metadata-Version: 1.0
Name: python-lust
Version: 1.0.7
Summary: Python Little Unix Server Toolkit
Home-page: http://pypi.python.org/pypi/python-lust
Author: Zed A. Shaw
Author-email: zedshaw@zedshaw.com
License: UNKNOWN
Download-URL: http://pypi.python.org/pypi/python-lust
Platform: UNKNOWN
